vinplots/__init__.py
vinplots/_color_palettes/_ColorPalettes.py
vinplots/_color_palettes/__init__.py
vinplots/_color_palettes/_palette_pkl_src/BlueSand_palette.pkl
vinplots/_color_palettes/_palette_pkl_src/BuOr_palette.pkl
vinplots/_color_palettes/_palette_pkl_src/LARRY_in_vitro_palette.pkl
vinplots/_color_palettes/_palette_pkl_src/__init__.py
vinplots/_color_palettes/_palette_pkl_src/pbmc3k_palette.pkl
vinplots/_color_palettes/_palette_pkl_src/share_seq_palette.pkl
vinplots/_color_palettes/_palette_pkl_src/warm_palette.pkl
vinplots/_construction/__init__.py
vinplots/_construction/_construct_plot_layout.py
vinplots/_construction/_default_matplotlib_fig_dims.py
vinplots/_construction/_linearize_axes.py
vinplots/_construction/_save_figure.py
vinplots/_plot/_Plot.py
vinplots/_plot/__init__.py
vinplots/_plot/_quick_plot.py
vinplots/_style/__init__.py
vinplots/_style/_modify_axis_spines.py
vinplots/_utilities/__init__.py
vinplots/_utilities/_setup_matplotlib_params.py
vinplots-0.0.75.dist-info/LICENSE
vinplots-0.0.75.dist-info/METADATA
vinplots-0.0.75.dist-info/WHEEL
vinplots-0.0.75.dist-info/top_level.txt
vinplots-0.0.75.dist-info/RECORD
