Metadata-Version: 2.1
Name: vinplots
Version: 0.0.75
Summary: vinplots - plotting assistant
Home-page: https://github.com/mvinyard/vinplots
Author: Michael E. Vinyard - Harvard University - Massachussetts General Hospital - Broad Institute of MIT and Harvard
Author-email: mvinyard@broadinstitute.org
License: MIT
Classifier: Development Status :: 2 - Pre-Alpha
Classifier: Programming Language :: Python :: 3.7
Classifier: Intended Audience :: Science/Research
Classifier: Topic :: Scientific/Engineering :: Bio-Informatics
Requires-Python: >3.7.0
License-File: LICENSE
Requires-Dist: matplotlib (>=3.4)
Requires-Dist: numpy (>=1.19.2)
Requires-Dist: pandas (>=1.1.2)
Requires-Dist: licorice-font (>=0.0.3)
Requires-Dist: pydk (>=0.0.54)
